[
  {
    "type": "card",
    "cardnumber": "4273-6623-8686-4599",
    "firstname": "Winfred",
    "lastname": "Raftery",
    "street": "3965 I-80 E Off Ramp",
    "mobile": "+1-617-555-1371",
    "sms": true,
    "city": {
      "name": "Uxbridge",
      "code": "MA",
      "state": "Massachusetts",
      "county": "Worcester",
      "display": "Uxbridge"
    },
    "issued": "11/15",
    "expiry": "6/19",
    "ccv": 736,
    "issuer": "Helena National Bank",
    "maxcredit": 1000,
    "threshold": 9500,
    "country": "US",
    "currency": "USD"
  },
  {
    "type": "card",
    "cardnumber": "4163-4174-9281-3991",
    "firstname": "Francoise",
    "lastname": "Navar",
    "street": "134 Yacht Rd",
    "mobile": "+1-334-555-9369",
    "sms": true,
    "city": {
      "name": "Skillman",
      "code": "NJ",
      "state": "New Jersey",
      "county": "Somerset",
      "display": "Montgomery"
    },
    "issued": "1/17",
    "expiry": "3/21",
    "ccv": 213,
    "issuer": "First National Bank of Las Animas",
    "maxcredit": 15000,
    "threshold": 12000,
    "country": "US",
    "currency": "USD"
  },
  {
    "type": "card",
    "cardnumber": "5677-7414-8288-4326",
    "firstname": "Exie",
    "lastname": "Barclift",
    "street": "4907 Lomita Ave",
    "mobile": "+1-334-555-9369",
    "sms": true,
    "city": {
      "name": "Meriden",
      "code": "IA",
      "state": "Iowa",
      "county": "Cherokee",
      "display": "Meriden"
    },
    "issued": "5/16",
    "expiry": "9/20",
    "ccv": 467,
    "issuer": "Waterford Bank, National Association",
    "maxcredit": 25000,
    "threshold": 22000,
    "country": "US",
    "currency": "USD"
  },
  {
    "type": "card",
    "cardnumber": "5920-7728-6813-5867",
    "firstname": "Krista",
    "lastname": "Barde",
    "street": "4582 Clinton Park",
    "mobile": "+1-502-555-124",
    "sms": true,
    "city": {
      "name": "Ponte Vedra Beach",
      "code": "FL",
      "state": "Florida",
      "county": "Saint Johns",
      "display": "Ponte Vedra Beach"
    },
    "issued": "2/14",
    "expiry": "4/18",
    "ccv": 649,
    "issuer": "Superior National Bank & Trust Company",
    "maxcredit": 30000,
    "threshold": 25000,
    "country": "US",
    "currency": "USD"
  },
  {
    "type": "card",
    "cardnumber": "4205-1834-8271-9835",
    "firstname": "Eli",
    "lastname": "Stenn",
    "street": "4364 Mcallister St",
    "mobile": "+1-717-555-3607",
    "sms": true,
    "city": {
      "name": "Koppel",
      "code": "PA",
      "state": "Pennsylvania",
      "county": "Beaver",
      "display": "Koppel"
    },
    "issued": "7/16",
    "expiry": "5/20",
    "ccv": 952,
    "issuer": "American National Bank - Fox Cities",
    "maxcredit": 10000,
    "threshold": 7000,
    "country": "US",
    "currency": "USD"
  },
  {
    "type": "card",
    "cardnumber": "3205-9894-1221-0005",
    "firstname": "Jake",
    "lastname": "Smith",
    "street": "3250 Olcott Street",
    "mobile": "+1-916-555-1836",
    "sms": true,
    "city": {
      "name": "Santa Clara",
      "code": "CA",
      "state": "California",
      "county": "Santa Clara",
      "display": "Santa Clara"
    },
    "issued": "10/15",
    "expiry": "9/20",
    "ccv": 912,
    "issuer": "Chase JP Morgan",
    "maxcredit": 10000,
    "threshold": 7000,
    "country": "US",
    "currency": "USD"
  },
  {
    "type": "card",
    "cardnumber": "4885-1834-8271-9888",
    "firstname": "Eli",
    "lastname": "Stenn",
    "street": "45 St. John's Road",
    "mobile": "+44-20-8759-9036",
    "sms": true,
    "city": {
      "name": "Motherwell",
      "code": "ML12 6MX",
      "county": "Biggar",
      "display": "Motherwell Biggar"
    },
    "issued": "8/17",
    "expiry": "5/22",
    "ccv": 321,
    "issuer": "Barclays PLC",
    "maxcredit": 2500,
    "threshold": 1000,
    "country": "UK",
    "currency": "GBP"
  }
]
